warez/__init__.py
warez/__main__.py
warez/pkg/__init__.py
warez/pkg/discover.py
warez/pkg/install.py
warez/pkg/licensing/__init__.py
warez/pkg/licensing/licenses.json
warez/pkg/listing.py
warez/pkg/runinenv
warez/pkg/system.py
warez/src/__init__.py
warez/src/git.py
warez-0.0.24.dist-info/entry_points.txt
warez-0.0.24.dist-info/WHEEL
warez-0.0.24.dist-info/METADATA
warez-0.0.24.dist-info/RECORD
