Metadata-Version: 2.1
Name: warez
Version: 0.0.24
Summary: tools for decentralized software development
License: MIT
Author: Angelo Gladding
Author-email: angelo@ragt.ag
Requires-Python: >=3.9,<3.11
Classifier: License :: OSI Approved :: MIT License
Classifier: Programming Language :: Python :: 3
Classifier: Programming Language :: Python :: 3.9
Requires-Dist: clicks (>=0.0.61,<0.0.62)
Requires-Dist: pendulum (>=2.1.2,<3.0.0)
Requires-Dist: radon (>=5.1.0,<6.0.0)
